{
  "project_info": {
    "project_number": "563622116007",
    "project_id": "sportsapp-32ae3",
    "storage_bucket": "sportsapp-32ae3.appspot.com"
  },
  "client": [
    {
      "client_info": {
        "mobilesdk_app_id": "1:563622116007:android:711ef8a255bf11e98eb982",
        "android_client_info": {
          "package_name": "com.example.abhithakur"
        }
      },
      "oauth_client": [
        {
          "client_id": "563622116007-krubklfahnurd8fsichge14buecbjr84.apps.googleusercontent.com",
          "client_type": 3
        }
      ],
      "api_key": [
        {
          "current_key": "AIzaSyBYrImZpz-VDrcZdavdGW80WBEAFBdgxHM"
        }
      ],
      "services": {
        "appinvite_service": {
          "other_platform_oauth_client": [
            {
              "client_id": "563622116007-krubklfahnurd8fsichge14buecbjr84.apps.googleusercontent.com",
              "client_type": 3
            }
          ]
        }
      }
    },
    {
      "client_info": {
        "mobilesdk_app_id": "1:563622116007:android:93ae0c06ea61f9e18eb982",
        "android_client_info": {
          "package_name": "com.example.adminapp"
        }
      },
      "oauth_client": [
        {
          "client_id": "563622116007-krubklfahnurd8fsichge14buecbjr84.apps.googleusercontent.com",
          "client_type": 3
        }
      ],
      "api_key": [
        {
          "current_key": "AIzaSyBYrImZpz-VDrcZdavdGW80WBEAFBdgxHM"
        }
      ],
      "services": {
        "appinvite_service": {
          "other_platform_oauth_client": [
            {
              "client_id": "563622116007-krubklfahnurd8fsichge14buecbjr84.apps.googleusercontent.com",
              "client_type": 3
            }
          ]
        }
      }
    }
  ],
  "configuration_version": "1"
}